LICENSE
MANIFEST.in
README.md
pyproject.toml
setup.cfg
radian/__init__.py
radian/__main__.py
radian/app.py
radian/completion.py
radian/console.py
radian/dispatch.py
radian/document.py
radian/io.py
radian/key_bindings.py
radian/lexer.py
radian/prompt_session.py
radian/rutils.py
radian/settings.py
radian/shell.py
radian.egg-info/PKG-INFO
radian.egg-info/SOURCES.txt
radian.egg-info/dependency_links.txt
radian.egg-info/entry_points.txt
radian.egg-info/requires.txt
radian.egg-info/top_level.txt
radian/latex/__init__.py
radian/latex/latex_symbols.py
radian/lineedit/__init__.py
radian/lineedit/buffer.py
radian/lineedit/history.py
radian/lineedit/prompt.py
radian/reticulate/__init__.py
radian/reticulate/config.R
radian/reticulate/key_bindings.R
tests/test_aaa.py
tests/test_readline.py
tests/test_reticulate.py
tests/test_shell.py
tests/test_startup.py
tests/test_version.py