Metadata-Version: 2.4
Name: radian
Version: 0.6.14
Summary: A 21 century R console
Author-email: Randy Lai <randy.cs.lai@gmail.com>
License: The MIT License (MIT)
Project-URL: Homepage, https://github.com/randy3k/radian
Requires-Python: >=3.7
License-File: LICENSE
Requires-Dist: rchitect<0.5.0,>=0.4.8
Requires-Dist: prompt_toolkit<3.1,>=3.0.41
Requires-Dist: pygments>=2.5.0
Provides-Extra: dev
Requires-Dist: coverage; extra == "dev"
Requires-Dist: pytest; extra == "dev"
Requires-Dist: pyte>=0.8.0; extra == "dev"
Requires-Dist: pexpect; extra == "dev"
Requires-Dist: pywinpty; sys_platform == "win32" and extra == "dev"
Requires-Dist: ptyprocess; sys_platform != "win32" and extra == "dev"
Dynamic: license-file
